{
	"clientID": "cleintID",
	"clientSecret": "clientSecret",
	"url": "http://locahost:8001",
	"front_url": "http://localhost:8080",
	"redirect_url": "https://local-redirect.data-ensta.fr/?port=8080",
	"port": 8001,
	"scopes": [
		"https://www.googleapis.com/auth/calendar.readonly",
		"https://www.googleapis.com/auth/drive.readonly",
		"https://www.googleapis.com/auth/userinfo.profile"
	]
}


"https://www.googleapis.com/auth/profile.agerange.read",
"https://www.googleapis.com/auth/user.addresses.read",
"https://www.googleapis.com/auth/profile.agerange.read",
"https://www.googleapis.com/auth/user.emails.read"
